corvus/__init__.py
corvus/cli.py
corvus/config.py
corvus/model_output.py
corvus/utils.py
corvus_ml-0.0.1.dist-info/METADATA
corvus_ml-0.0.1.dist-info/entry_points.txt
corvus_ml-0.0.1.dist-info/WHEEL
corvus_ml-0.0.1.dist-info/RECORD
