Metadata-Version: 2.1
Name: corvus-ml
Version: 0.0.1
Summary: Search ShareableAI Models
License: LGPL-3.0-or-later
Author: Lissa Hyacinth
Author-email: lissa@shareableai.com
Requires-Python: >=3.8,<4.0
Classifier: License :: OSI Approved :: GNU Lesser General Public License v3 or later (LGPLv3+)
Classifier: Programming Language :: Python :: 3
Classifier: Programming Language :: Python :: 3.8
Classifier: Programming Language :: Python :: 3.9
Classifier: Programming Language :: Python :: 3.10
Classifier: Programming Language :: Python :: 3.11
Requires-Dist: click (>=8,<9)
Requires-Dist: jackdaw-ml (>=0.0.5)
Requires-Dist: rich (>=13,<14)
Requires-Dist: setuptools (>=67.0.0)
Requires-Dist: tomli (==2.0.1)
Requires-Dist: tomli-w (==1.0.0)
